{"name":"Header","type":"header","sections":{"announcement-bar":{"type":"announcement-bar","blocks":{"announcement_iApH88":{"type":"announcement","settings":{"background-color":"#008bfc","text-color":"#ffffff","text":"Get your 20% off with code","code":"SOCIAL10","utmcode":"social"}},"announcement-bar-0":{"type":"announcement","settings":{"background-color":"#008bfc","text-color":"#ffffff","text":"Get your 15% off with code","code":"WELCOME","utmcode":"email"}}},"block_order":["announcement_iApH88","announcement-bar-0"],"settings":{"close-color":"#ffffff"}}},"order":["announcement-bar"]}